serac/__init__.py
serac/__main__.py
serac/commands.py
serac/config.py
serac/crypto.py
serac/exceptions.py
serac/reporter.py
serac/index/__init__.py
serac/index/database.py
serac/index/index.py
serac/index/models.py
serac/storage/__init__.py
serac/storage/base.py
serac/storage/local.py
serac/storage/s3.py
serac-0.0.1.dist-info/LICENSE
serac-0.0.1.dist-info/METADATA
serac-0.0.1.dist-info/WHEEL
serac-0.0.1.dist-info/dependency_links.txt
serac-0.0.1.dist-info/entry_points.txt
serac-0.0.1.dist-info/top_level.txt
serac-0.0.1.dist-info/zip-safe
serac-0.0.1.dist-info/RECORD
