Metadata-Version: 2.1
Name: serac
Version: 0.0.1
Summary: Incremental permanent data archiver with encryption
Home-page: http://radiac.net/projects/serac/
Author: Richard Terry
Author-email: code@radiac.net
License: BSD
Keywords: backup archive glacier
Platform: UNKNOWN
Classifier: Development Status :: 4 - Beta
Classifier: Intended Audience :: Developers
Classifier: License :: OSI Approved :: BSD License
Classifier: Operating System :: OS Independent
Classifier: Topic :: System :: Archiving :: Backup
Classifier: Programming Language :: Python :: 3
Classifier: Programming Language :: Python :: 3.7
Requires-Dist: click
Requires-Dist: peewee
Requires-Dist: pyAesCrypt
Requires-Dist: smart-open
